{
  "db_name": "PostgreSQL",
  "query": "\n        SELECT g.id, g.image_url, g.caption,\n               u.discord_id as uploader_discord_id,\n               u.discord_display_name as uploader_display_name,\n               g.created_at\n        FROM gallery_images g\n        JOIN users u ON u.id = g.uploaded_by_user_id\n        WHERE g.club_id = $1 AND g.status = 'approved'\n        ORDER BY g.created_at DESC\n        LIMIT $2 OFFSET $3\n        ",
  "describe": {
    "columns": [
      {
        "ordinal": 0,
        "name": "id",
        "type_info": "Uuid"
      },
      {
        "ordinal": 1,
        "name": "image_url",
        "type_info": "Text"
      },
      {
        "ordinal": 2,
        "name": "caption",
        "type_info": "Text"
      },
      {
        "ordinal": 3,
        "name": "uploader_discord_id",
        "type_info": "Text"
      },
      {
        "ordinal": 4,
        "name": "uploader_display_name",
        "type_info": "Text"
      },
      {
        "ordinal": 5,
        "name": "created_at",
        "type_info": "Timestamptz"
      }
    ],
    "parameters": {
      "Left": [
        "Uuid",
        "Int8",
        "Int8"
      ]
    },
    "nullable": [
      false,
      false,
      true,
      false,
      false,
      false
    ]
  },
  "hash": "e8d1b5065092b3db065a658850c9a1ab49d4819858a7889c791ed6cc27bba6f2"
}
